osc_rule_based_extractor-0.1.0.dist-info/METADATA
osc_rule_based_extractor-0.1.0.dist-info/WHEEL
osc_rule_based_extractor-0.1.0.dist-info/entry_points.txt
osc_rule_based_extractor-0.1.0.dist-info/licenses/AUTHORS.rst
osc_rule_based_extractor-0.1.0.dist-info/licenses/LICENSE.txt
osc_rule_based_extractor/__init__.py
osc_rule_based_extractor/skeleton.py
osc_rule_based_extractor-0.1.0.dist-info/RECORD
