Metadata-Version: 2.1
Name: osc-rule-based-extractor
Version: 0.1.0
Summary: OS-Climate Data Extraction Tool
Author-Email: David Besslich <90916810+DaBeIDS@users.noreply.github.com>
License:                                  Apache License
Classifier: Intended Audience :: Developers
Classifier: Intended Audience :: Science/Research
Classifier: License :: OSI Approved :: Apache Software License
Classifier: Operating System :: MacOS
Classifier: Operating System :: Microsoft :: Windows
Classifier: Operating System :: Unix
Classifier: Programming Language :: Python
Classifier: Programming Language :: Python :: 3
Classifier: Programming Language :: Python :: 3 :: Only
Classifier: Programming Language :: Python :: 3.11
Classifier: Programming Language :: Python :: 3.10
Classifier: Programming Language :: Python :: 3.9
Classifier: Topic :: Office/Business :: Financial
Classifier: Topic :: Scientific/Engineering
Classifier: Topic :: Software Development
Project-URL: Homepage, https://github.com/os-climate/osc-rule-based-extractor
Project-URL: Repository, https://github.com/os-climate/osc-rule-based-extractor
Project-URL: Downloads, https://github.com/os-climate/osc-rule-based-extractor/releases
Project-URL: Bug tracker, https://github.com/os-climate/osc-rule-based-extractor/issues
Project-URL: Documentation, https://github.com/os-climate/osc-rule-based-extractor/tree/main/docs
Project-URL: Source code, https://github.com/os-climate/osc-rule-based-extractor
Requires-Python: >=3.9
Provides-Extra: dev
Provides-Extra: test
Requires-Dist: pylint; extra == "dev"
Requires-Dist: toml; extra == "dev"
Requires-Dist: yapf; extra == "dev"
Requires-Dist: pdm; extra == "dev"
Requires-Dist: pytest; extra == "test"
Requires-Dist: pytest-cov; extra == "test"
